Metadata-Version: 2.1
Name: asimtools
Version: 0.1.0
Summary: A lightweight python package for managing and running atomic simulation workflows
Author-email: Keith Phuthi <mkphuthi@gmail.com>
Maintainer-email: Keith Phuthi <mkphuthi@gmail.com>
License: MIT
Project-URL: repository, https://github.com/BattModels/asimtools
Project-URL: issues, https://github.com/BattModels/asimtools/issues
Project-URL: documentation, https://battmodels.github.io/asimtools/
Keywords: high-throughput,workflow,atomistic,simulation
Classifier: Programming Language :: Python :: 3
Classifier: License :: OSI Approved :: MIT License
Classifier: Topic :: Scientific/Engineering
Classifier: Intended Audience :: Science/Research
Classifier: Development Status :: 4 - Beta
Classifier: Operating System :: MacOS
Classifier: Operating System :: Unix
Requires-Python: >=3.9
License-File: LICENSE
Requires-Dist: pandas
Requires-Dist: pyyaml
Requires-Dist: pymatgen
Requires-Dist: ase>=3.22.1
Requires-Dist: colorama
Requires-Dist: natsort
Requires-Dist: mp-api
Provides-Extra: dev
Requires-Dist: asimtools[docs,phonons,tests]; extra == "dev"
Provides-Extra: mlip
Requires-Dist: matgl>=1.1.2; extra == "mlip"
Requires-Dist: chgnet>=0.3.3; extra == "mlip"
Requires-Dist: mace-torch>=0.3.3; extra == "mlip"
Provides-Extra: phonons
Requires-Dist: phonopy>=2.20.0; extra == "phonons"
Requires-Dist: seekpath>=2.1.0; extra == "phonons"
Provides-Extra: tests
Requires-Dist: pytest>=7.4.0; extra == "tests"
Requires-Dist: pytest-cov>=3.0.0; extra == "tests"
Provides-Extra: docs
Requires-Dist: sphinx; extra == "docs"
Requires-Dist: sphinx-rtd-theme; extra == "docs"
Requires-Dist: myst-parser; extra == "docs"
